comod/__init__.py
comod/base.py
comod/common.py
comod/community.py
comod/data.py
comod/models.py
comod-0.2.1.dist-info/LICENSE.txt
comod-0.2.1.dist-info/METADATA
comod-0.2.1.dist-info/WHEEL
comod-0.2.1.dist-info/top_level.txt
comod-0.2.1.dist-info/RECORD
