Metadata-Version: 2.1
Name: comod
Version: 0.2.1
Summary: Compartmental modelling Python package
Home-page: https://github.com/dih5/comod
Author: Dih5
Author-email: dihedralfive@gmail.com
License: UNKNOWN
Platform: UNKNOWN
Classifier: Development Status :: 3 - Alpha
Classifier: Intended Audience :: Science/Research
Classifier: License :: OSI Approved :: MIT License
Classifier: Natural Language :: English
Classifier: Programming Language :: Python :: 3
Classifier: Programming Language :: Python :: 3.5
Classifier: Programming Language :: Python :: 3.6
Classifier: Programming Language :: Python :: 3.7
Classifier: Programming Language :: Python :: 3.8
License-File: LICENSE.txt
Requires-Dist: numpy
Requires-Dist: scipy
Requires-Dist: pandas
Provides-Extra: docs
Requires-Dist: nbsphinx ; extra == 'docs'
Requires-Dist: sphinx-rtd-theme ; extra == 'docs'
Requires-Dist: IPython ; extra == 'docs'
Requires-Dist: sympy ; extra == 'docs'
Requires-Dist: network2tikz ; extra == 'docs'
Requires-Dist: pdf2image ; extra == 'docs'
Requires-Dist: python-igraph ; extra == 'docs'
Provides-Extra: extras
Requires-Dist: sympy ; extra == 'extras'
Requires-Dist: network2tikz ; extra == 'extras'
Requires-Dist: pdf2image ; extra == 'extras'
Requires-Dist: python-igraph ; extra == 'extras'
Provides-Extra: test
Requires-Dist: pytest ; extra == 'test'
Requires-Dist: sympy ; extra == 'test'
Requires-Dist: network2tikz ; extra == 'test'
Requires-Dist: pdf2image ; extra == 'test'
Requires-Dist: python-igraph ; extra == 'test'
